{
  "$schema": "https://json-schema.org/draft/2020-12/schema",
  "type": "object",
  "additionalProperties": false,
  "properties": {
    "whitelist": {
      "type": "array",
      "items": {
        "type": "string"
      }
    },
    "stats_public": {
      "type": "object",
      "patternProperties": {
        ".+": {
          "type": "object",
          "properties": {
            "value": {
              "type": "integer"
            },
            "additional_properties": {
              "type": "object",
              "patternProperties": {
                ".+": {
                  "type": "string"
                }
              }
            }
          },
          "additionalProperties": false
        }
      }
    },
    "stats_private": {
      "type": "object",
      "patternProperties": {
        ".+": {
          "type": "object",
          "properties": {
            "value": {
              "type": "integer"
            },
            "additional_properties": {
              "type": "object",
              "patternProperties": {
                ".+": {
                  "type": "string"
                }
              }
            }
          },
          "additionalProperties": false
        }
      }
    }
  }
}
